Workbook

Sheet Report
A2: Financial KPI report — 28 metrics
A3: Company | B3: =IF(Inputs!B2<>"",Inputs!B2,"")
A4: Fiscal year / currency | B4: =IF(ISNUMBER(Inputs!C3),Inputs!C3,"") | C4: =IF(Inputs!C4<>"",Inputs!C4,"")
A6: Metric | B6: Result | C6: Basis / units | D6: Input status at build | E6: Details at build
A7: Revenue growth YoY | B7: =IF(ISNUMBER(Calculations!B2),Calculations!B2,"") | C7: Annual / FY-end basis
A8: EBITDA margin | B8: =IF(ISNUMBER(Calculations!B3),Calculations!B3,"") | C8: Annual / FY-end basis
A9: Net debt | B9: =IF(ISNUMBER(Calculations!B4),Calculations!B4,"") | C9: =IF(Inputs!C4<>"",Inputs!C4&", millions","")
A10: Net debt / EBITDA | B10: =IF(ISNUMBER(Calculations!B5),Calculations!B5,"") | C10: Multiple
A11: ARR | B11: =IF(ISNUMBER(Calculations!B6),Calculations!B6,"") | C11: =IF(Inputs!C4<>"",Inputs!C4&", millions","")
A12: WACC | B12: =IF(ISNUMBER(Calculations!B7),Calculations!B7,"") | C12: Market weights / CAPM
A13: Gross margin | B13: =IF(ISNUMBER(Calculations!B8),Calculations!B8,"") | C13: Annual / FY-end basis
A14: EBIT margin | B14: =IF(ISNUMBER(Calculations!B9),Calculations!B9,"") | C14: Annual / FY-end basis
A15: Net profit margin | B15: =IF(ISNUMBER(Calculations!B10),Calculations!B10,"") | C15: Annual / FY-end basis
A16: Free cash flow | B16: =IF(ISNUMBER(Calculations!B11),Calculations!B11,"") | C16: =IF(Inputs!C4<>"",Inputs!C4&", millions","")
A17: FCF margin | B17: =IF(ISNUMBER(Calculations!B12),Calculations!B12,"") | C17: Annual / FY-end basis
A18: Current ratio | B18: =IF(ISNUMBER(Calculations!B13),Calculations!B13,"") | C18: Multiple
A19: Quick ratio | B19: =IF(ISNUMBER(Calculations!B14),Calculations!B14,"") | C19: Multiple
A20: Interest coverage | B20: =IF(ISNUMBER(Calculations!B15),Calculations!B15,"") | C20: Multiple
A21: Return on assets | B21: =IF(ISNUMBER(Calculations!B16),Calculations!B16,"") | C21: Annual / FY-end basis
A22: Return on equity | B22: =IF(ISNUMBER(Calculations!B17),Calculations!B17,"") | C22: Annual / FY-end basis
A23: Enterprise value (simplified) | B23: =IF(ISNUMBER(Calculations!B18),Calculations!B18,"") | C23: =IF(Inputs!C4<>"",Inputs!C4&", millions","")
A24: EV / Revenue | B24: =IF(ISNUMBER(Calculations!B19),Calculations!B19,"") | C24: Multiple
A25: EV / EBITDA | B25: =IF(ISNUMBER(Calculations!B20),Calculations!B20,"") | C25: Multiple
A26: P/E | B26: =IF(ISNUMBER(Calculations!B21),Calculations!B21,"") | C26: Multiple
A27: Revenue CAGR | B27: =IF(ISNUMBER(Calculations!B22),Calculations!B22,"") | C27: Annual / FY-end basis
A28: EBITDA CAGR | B28: =IF(ISNUMBER(Calculations!B23),Calculations!B23,"") | C28: Annual / FY-end basis
A29: Net leverage change YoY | B29: =IF(ISNUMBER(Calculations!B24),Calculations!B24,"") | C29: Change in turns
A30: Cash conversion (CFO / EBITDA) | B30: =IF(ISNUMBER(Calculations!B25),Calculations!B25,"") | C30: Annual / FY-end basis
A31: Days sales outstanding | B31: =IF(ISNUMBER(Calculations!B26),Calculations!B26,"") | C31: 365-day convention
A32: Days inventory outstanding | B32: =IF(ISNUMBER(Calculations!B27),Calculations!B27,"") | C32: 365-day convention
A33: Days payable outstanding | B33: =IF(ISNUMBER(Calculations!B28),Calculations!B28,"") | C33: 365-day convention
A34: Cash conversion cycle (CCC) | B34: =IF(ISNUMBER(Calculations!B29),Calculations!B29,"") | C34: 365-day convention
A37: Calculation state
A40: Statuses describe imported data at build time. Rerun after editing inputs.
A41: CAGR: first to latest FY. ROA/ROE: average balances. Cash conversion: CFO / EBITDA.
A42: CCC: DSO + DIO - DPO; revenue and COGS are documented credit-sales/purchases proxies.

Sheet Assumptions
A2: Explicit cost-of-capital assumptions
A4: Assumption | B4: Explicit FY-end value
A5: Market value of debt (millions)
A6: Pre tax cost of debt
A7: Risk free rate
A8: Equity beta
A9: Equity risk premium
A10: Marginal tax rate
A12: Rates are fractions (0.04 = 4%). No assumptions are estimated.
A13: Market debt is explicit; reported/book debt is not substituted.
A14: WACC: two capital components, CAPM cost of equity.

Sheet Calculations
A1: Template-owned formulas. Money displayed in millions; days use a 365-day convention.
A2: Revenue growth YoY | B2: =IF(AND(ISNUMBER(Inputs!B7),ISNUMBER(Inputs!C7),Inputs!B7<>0),Inputs!C7/Inputs!B7-1,"")
A3: EBITDA margin | B3: =IF(AND(ISNUMBER(Inputs!C8),ISNUMBER(Inputs!C7),Inputs!C7<>0),Inputs!C8/Inputs!C7,"")
A4: Net debt | B4: =IF(AND(ISNUMBER(Inputs!C9),ISNUMBER(Inputs!C10)),Inputs!C9-Inputs!C10,"")
A5: Net debt / EBITDA | B5: =IF(AND(ISNUMBER(Inputs!C9),ISNUMBER(Inputs!C10),ISNUMBER(Inputs!C8),Inputs!C8>0,ISNUMBER(Calculations!B4)),B4/Inputs!C8,"")
A6: ARR | B6: =IF(AND(ISNUMBER(Inputs!C30),Inputs!C30>=0),Inputs!C30*12,"")
A7: WACC | B7: =IF(AND(ISNUMBER(Inputs!C27),ISNUMBER(Assumptions!B5),ISNUMBER(Assumptions!B6),ISNUMBER(Assumptions!B7),ISNUMBER(Assumptions!B8),ISNUMBER(Assumptions!B9),ISNUMBER(Assumptions!B10),Inputs!C27>=0,Assumptions!B5>=0,SUM(Inputs!C27,Assumptions!B5)>0,Assumptions!B6>=0,Assumptions!B9>=0,Assumptions!B10>=0,Assumptions!B10<=1),Inputs!C27/SUM(Inputs!C27,Assumptions!B5)*(Assumptions!B7+Assumptions!B8*Assumptions!B9)+Assumptions!B5/SUM(Inputs!C27,Assumptions!B5)*Assumptions!B6*(1-Assumptions!B10),"")
A8: Gross margin | B8: =IF(AND(ISNUMBER(Inputs!C12),ISNUMBER(Inputs!C7),Inputs!C7>0),Inputs!C12/Inputs!C7,"")
A9: EBIT margin | B9: =IF(AND(ISNUMBER(Inputs!C13),ISNUMBER(Inputs!C7),Inputs!C7>0),Inputs!C13/Inputs!C7,"")
A10: Net profit margin | B10: =IF(AND(ISNUMBER(Inputs!C14),ISNUMBER(Inputs!C7),Inputs!C7>0),Inputs!C14/Inputs!C7,"")
A11: Free cash flow | B11: =IF(AND(ISNUMBER(Inputs!C17),ISNUMBER(Inputs!C18),Inputs!C18>=0),Inputs!C17-Inputs!C18,"")
A12: FCF margin | B12: =IF(AND(ISNUMBER(Inputs!C17),ISNUMBER(Inputs!C18),ISNUMBER(Inputs!C7),Inputs!C18>=0,Inputs!C7>0,ISNUMBER(Calculations!B11)),Calculations!B11/Inputs!C7,"")
A13: Current ratio | B13: =IF(AND(ISNUMBER(Inputs!C22),ISNUMBER(Inputs!C23),Inputs!C22>=0,Inputs!C23>0),Inputs!C22/Inputs!C23,"")
A14: Quick ratio | B14: =IF(AND(ISNUMBER(Inputs!C22),ISNUMBER(Inputs!C24),ISNUMBER(Inputs!C23),Inputs!C22>=0,Inputs!C23>0,Inputs!C24>=0,Inputs!C24<=Inputs!C22),(Inputs!C22-Inputs!C24)/Inputs!C23,"")
A15: Interest coverage | B15: =IF(AND(ISNUMBER(Inputs!C13),ISNUMBER(Inputs!C15),Inputs!C15>0),Inputs!C13/Inputs!C15,"")
A16: Return on assets | B16: =IF(AND(ISNUMBER(Inputs!C14),ISNUMBER(Inputs!B20),ISNUMBER(Inputs!C20),Inputs!B20>=0,Inputs!C20>=0,SUM(Inputs!B20,Inputs!C20)>0),Inputs!C14/AVERAGE(Inputs!B20,Inputs!C20),"")
A17: Return on equity | B17: =IF(AND(ISNUMBER(Inputs!C14),ISNUMBER(Inputs!B21),ISNUMBER(Inputs!C21),Inputs!B21>=0,Inputs!C21>=0,SUM(Inputs!B21,Inputs!C21)>0),Inputs!C14/AVERAGE(Inputs!B21,Inputs!C21),"")
A18: Enterprise value (simplified) | B18: =IF(AND(ISNUMBER(Inputs!C27),ISNUMBER(Inputs!C9),ISNUMBER(Inputs!C10),Inputs!C27>=0,Inputs!C9>=0,Inputs!C10>=0),Inputs!C27+Inputs!C9-Inputs!C10,"")
A19: EV / Revenue | B19: =IF(AND(ISNUMBER(Inputs!C27),ISNUMBER(Inputs!C9),ISNUMBER(Inputs!C10),ISNUMBER(Inputs!C7),Inputs!C27>=0,Inputs!C9>=0,Inputs!C10>=0,Inputs!C7>0,ISNUMBER(Calculations!B18)),Calculations!B18/Inputs!C7,"")
A20: EV / EBITDA | B20: =IF(AND(ISNUMBER(Inputs!C27),ISNUMBER(Inputs!C9),ISNUMBER(Inputs!C10),ISNUMBER(Inputs!C8),Inputs!C27>=0,Inputs!C9>=0,Inputs!C10>=0,Inputs!C8>0,ISNUMBER(Calculations!B18)),Calculations!B18/Inputs!C8,"")
A21: P/E | B21: =IF(AND(ISNUMBER(Inputs!C27),ISNUMBER(Inputs!C14),Inputs!C27>=0,Inputs!C14>0),Inputs!C27/Inputs!C14,"")
A22: Revenue CAGR | B22: =IF(AND(ISNUMBER(Inputs!D7),ISNUMBER(Inputs!C7),Inputs!D7>0,Inputs!C7>=0,ISNUMBER(Inputs!D3),ISNUMBER(Inputs!C3),Inputs!C3>Inputs!D3),(Inputs!C7/Inputs!D7)^(1/(Inputs!C3-Inputs!D3))-1,"")
A23: EBITDA CAGR | B23: =IF(AND(ISNUMBER(Inputs!D8),ISNUMBER(Inputs!C8),Inputs!D8>0,Inputs!C8>=0,ISNUMBER(Inputs!D3),ISNUMBER(Inputs!C3),Inputs!C3>Inputs!D3),(Inputs!C8/Inputs!D8)^(1/(Inputs!C3-Inputs!D3))-1,"")
A24: Net leverage change YoY | B24: =IF(AND(ISNUMBER(Inputs!B9),ISNUMBER(Inputs!C9),ISNUMBER(Inputs!B10),ISNUMBER(Inputs!C10),ISNUMBER(Inputs!B8),ISNUMBER(Inputs!C8),Inputs!B8>0,Inputs!C8>0,ISNUMBER(Calculations!B5)),B5-(Inputs!B9-Inputs!B10)/Inputs!B8,"")
A25: Cash conversion (CFO / EBITDA) | B25: =IF(AND(ISNUMBER(Inputs!C17),ISNUMBER(Inputs!C8),Inputs!C8>0),Inputs!C17/Inputs!C8,"")
A26: Days sales outstanding | B26: =IF(AND(ISNUMBER(Inputs!B25),ISNUMBER(Inputs!C25),ISNUMBER(Inputs!C7),Inputs!B25>=0,Inputs!C25>=0,Inputs!C7>0),AVERAGE(Inputs!B25,Inputs!C25)/Inputs!C7*365,"")
A27: Days inventory outstanding | B27: =IF(AND(ISNUMBER(Inputs!B24),ISNUMBER(Inputs!C24),ISNUMBER(Inputs!C11),Inputs!B24>=0,Inputs!C24>=0,Inputs!C11>0),AVERAGE(Inputs!B24,Inputs!C24)/Inputs!C11*365,"")
A28: Days payable outstanding | B28: =IF(AND(ISNUMBER(Inputs!B26),ISNUMBER(Inputs!C26),ISNUMBER(Inputs!C11),Inputs!B26>=0,Inputs!C26>=0,Inputs!C11>0),AVERAGE(Inputs!B26,Inputs!C26)/Inputs!C11*365,"")
A29: Cash conversion cycle (CCC) | B29: =IF(AND(ISNUMBER(Inputs!B25),ISNUMBER(Inputs!C25),ISNUMBER(Inputs!C7),ISNUMBER(Inputs!B24),ISNUMBER(Inputs!C24),ISNUMBER(Inputs!C11),ISNUMBER(Inputs!B26),ISNUMBER(Inputs!C26),Inputs!B25>=0,Inputs!C25>=0,Inputs!C7>0,Inputs!B24>=0,Inputs!C24>=0,Inputs!C11>0,Inputs!B26>=0,Inputs!C26>=0,ISNUMBER(Calculations!B26),ISNUMBER(Calculations!B27),ISNUMBER(Calculations!B28)),Calculations!B26+Calculations!B27-Calculations!B28,"")
A32: Unavailable inputs or invalid denominators leave results blank; see Checks.

Sheet Inputs
A2: Company
A3: Fiscal year
A4: Currency | B4: =IF(C4<>"",C4,"")
A5: Company ID / scope
A6: Amounts shown in millions | B6: Previous FY | C6: Latest FY | D6: First FY (CAGR only)
A7: Revenue
A8: EBITDA
A9: Total debt
A10: Cash and equivalents
A11: Cost of goods sold
A12: Gross profit
A13: EBIT
A14: Net income
A15: Interest expense
A16: Income tax expense
A17: Operating cash flow
A18: Capex (positive spending)
... A34: Share price is per share; shares are counts. Other money is shown in millions.

Sheet Checks
A2: Validation issues
A4: Severity | B4: Code | C4: Metric | D4: Company ID | E4: Message | F4: Source

Sheet Source_Map
A2: Source-to-cell lineage
A4: Source file | B4: Source sheet | C4: Source row | D4: Source column | E4: Locator | F4: Field | G4: Fiscal year | H4: Period | I4: Scope | J4: Currency | K4: Original value | L4: Original unit | M4: Normalized value | N4: Canonical unit | O4: Value status | P4: Destination | Q4: Dependent metrics

Sheet Data_Dictionary
A1: Template version | B1: 2
A2: Metric definitions
A4: Metric ID | B4: Label | C4: Formula / definition | D4: Required fields | E4: Unit | F4: Implementation | G4: Limitations
A5: revenue_growth_yoy | B5: Revenue growth YoY | C5: Revenue FY / Revenue FY-1 - 1 | D5: revenue:previous, revenue:latest | E5: % | F5: implemented | G5: Consecutive comparable fiscal years; nonzero prior revenue.
A6: ebitda_margin | B6: EBITDA margin | C6: EBITDA / Revenue | D6: ebitda:latest, revenue:latest | E6: % | F6: implemented | G6: Same FY, scope and currency; nonzero revenue.
A7: net_debt | B7: Net debt | C7: Total debt - Cash and equivalents | D7: total_debt:latest, cash_and_equivalents:latest | E7: currency | F7: implemented | G7: Both balances at the same fiscal year end; negative net debt is allowed.
A8: net_debt_to_ebitda | B8: Net debt / EBITDA | C8: Net debt / EBITDA | D8: total_debt:latest, cash_and_equivalents:latest, ebitda:latest | E8: x | F8: implemented | G8: Positive annual EBITDA required.
A9: arr | B9: ARR | C9: Explicit fiscal-year-end MRR x 12 | D9: monthly_recurring_revenue:latest | E9: currency | F9: implemented | G9: Annualized recurring run rate, not recognized annual revenue. Input MRR explicitly excludes nonrecurring revenue.
A10: wacc | B10: WACC | C10: E/(E+D)*(Rf+beta*ERP) + D/(E+D)*Kd*(1-tax) | D10: market_cap:latest, market_value_debt:latest, pre_tax_cost_of_debt:latest, risk_free_rate:latest, equity_beta:latest, equity_risk_premium:latest, marginal_tax_rate:latest | E10: % | F10: implemented | G10: Two-component CAPM model; explicit market equity/debt at FY end. Rates are decimal fractions; no book-debt substitution or inferred assumptions.
A11: gross_margin | B11: Gross margin | C11: gross_profit / Revenue | D11: gross_profit:latest, revenue:latest | E11: % | F11: implemented | G11: Reported numerator and positive annual revenue; no inferred numerator.
A12: ebit_margin | B12: EBIT margin | C12: ebit / Revenue | D12: ebit:latest, revenue:latest | E12: % | F12: implemented | G12: Reported numerator and positive annual revenue; no inferred numerator.
A13: net_profit_margin | B13: Net profit margin | C13: net_income / Revenue | D13: net_income:latest, revenue:latest | E13: % | F13: implemented | G13: Reported numerator and positive annual revenue; no inferred numerator.
A14: free_cash_flow | B14: Free cash flow | C14: Operating cash flow - positive capex spending | D14: cash_flow_from_operations:latest, capex:latest | E14: currency | F14: implemented | G14: CFO less capex spending; this is not FCFF or FCFE.
A15: fcf_margin | B15: FCF margin | C15: Free cash flow / Revenue | D15: cash_flow_from_operations:latest, capex:latest, revenue:latest | E15: % | F15: implemented | G15: Same FY and CFO-minus-capex convention.
... A32: cash_conversion_cycle | B32: Cash conversion cycle (CCC) | C32: DSO + DIO - DPO | D32: accounts_receivable:previous, accounts_receivable:latest, revenue:latest, inventory:previous, inventory:latest, cogs:latest, accounts_payable:previous, accounts_payable:latest | E32: days | F32: implemented | G32: Inherits DSO/DIO/DPO conventions. Negative CCC is valid. This is a duration, separate from CFO/EBITDA.
